sortingChengChung/BubbleSort.py
sortingChengChung/InsertionSort.py
sortingChengChung/QuickSort.py
sortingChengChung/SelectionSort.py
sortingChengChung/__init__.py
sortingChengChung-0.1.dist-info/METADATA
sortingChengChung-0.1.dist-info/WHEEL
sortingChengChung-0.1.dist-info/top_level.txt
sortingChengChung-0.1.dist-info/RECORD
